d1_scimeta/__init__.py
d1_scimeta/gen_root_xsd.py
d1_scimeta/lxml_validate.py
d1_scimeta/schema_prepare.py
d1_scimeta/schema_resolve.py
d1_scimeta/util.py
d1_scimeta/validate.py
d1_scimeta/ext/format_id_to_schema.json
d1_scimeta/ext/remove_empty_elements.xslt
d1_scimeta/ext/strip_whitespace.xslt
d1_scimeta/schema/_cache/http_dublincore.org_schemas_xmls_qdc_2008_02_11__dc.ORIGINAL.xsd
d1_scimeta/schema/_cache/http_dublincore.org_schemas_xmls_qdc_2008_02_11__dc.xsd
d1_scimeta/schema/_cache/http_dublincore.org_schemas_xmls_qdc_2008_02_11__dcmitype.xsd
d1_scimeta/schema/_cache/http_dublincore.org_schemas_xmls_qdc_2008_02_11__dcterms.ORIGINAL.xsd
d1_scimeta/schema/_cache/http_dublincore.org_schemas_xmls_qdc_2008_02_11__dcterms.xsd
d1_scimeta/schema/_cache/http_dublincore.org_schemas_xmls_qdc__dc.ORIGINAL.xsd
d1_scimeta/schema/_cache/http_dublincore.org_schemas_xmls_qdc__dc.xsd
d1_scimeta/schema/_cache/http_schemas.opengis.net_gml_3.1.1_smil__smil20-language.ORIGINAL.xsd
d1_scimeta/schema/_cache/http_schemas.opengis.net_gml_3.1.1_smil__smil20-language.xsd
d1_scimeta/schema/_cache/http_schemas.opengis.net_gml_3.1.1_smil__smil20.ORIGINAL.xsd
d1_scimeta/schema/_cache/http_schemas.opengis.net_gml_3.1.1_smil__smil20.xsd
d1_scimeta/schema/_cache/http_www.w3.org_1999__xlink.ORIGINAL.xsd
d1_scimeta/schema/_cache/http_www.w3.org_1999__xlink.xsd
d1_scimeta/schema/_cache/http_www.w3.org_2001_03__xml.xsd
d1_scimeta/schema/_cache/http_www.w3.org_2001__xml.xsd
d1_scimeta/schema/_cache/http_www.w3.org_2009_01__xml.xsd
d1_scimeta/schema/datacite-3.0/metadata.ORIGINAL.xsd
d1_scimeta/schema/datacite-3.0/metadata.xsd
d1_scimeta/schema/datacite-3.0/include/datacite-contributorType-v3.xsd
d1_scimeta/schema/datacite-3.0/include/datacite-dateType-v3.xsd
d1_scimeta/schema/datacite-3.0/include/datacite-descriptionType-v3.xsd
d1_scimeta/schema/datacite-3.0/include/datacite-relatedIdentifierType-v3.xsd
d1_scimeta/schema/datacite-3.0/include/datacite-relationType-v3.xsd
dataone.scimeta-3.5.2.dist-info/METADATA
dataone.scimeta-3.5.2.dist-info/WHEEL
dataone.scimeta-3.5.2.dist-info/top_level.txt
dataone.scimeta-3.5.2.dist-info/RECORD
