Metadata-Version: 2.1
Name: dataone.scimeta
Version: 3.5.2
Summary: Utilities for processing Science Metadata
Home-page: https://github.com/DataONEorg/d1_python
Author: DataONE Project
Author-email: developers@dataone.org
License: Apache License, Version 2.0
Keywords: DataONE client server member-node coordinating-node science metadata scimeta xml catalogue xsd validate
Classifier: Development Status :: 5 - Production/Stable
Classifier: Intended Audience :: Developers
Classifier: Topic :: Scientific/Engineering
Classifier: License :: OSI Approved :: Apache Software License
Classifier: Programming Language :: Python :: 3
Classifier: Programming Language :: Python :: 3.7
Requires-Dist: lxml (>=4.9.2)
